rangedf/__init__.py
rangedf/rangedf.py
rangedf-1.0.dist-info/licenses/LICENSE.txt
rangedf-1.0.dist-info/METADATA
rangedf-1.0.dist-info/WHEEL
rangedf-1.0.dist-info/top_level.txt
rangedf-1.0.dist-info/RECORD
