Metadata-Version: 2.4
Name: rangedf
Version: 1.0
Summary: Transform Tick Data into OHLCV Range Dataframe!
Author-email: Carlos Gabriel <carlgsr1@gmail.com>
License: MIT License
Project-URL: Homepage, https://github.com/srlcarlg/rangedf
Keywords: range,pyrange,rangepy,range chart,range ohlc,range bars,finance,candlestick,ohlc,market,investing,technical analysis
Classifier: Intended Audience :: Developers
Classifier: Intended Audience :: Financial and Insurance Industry
Classifier: Intended Audience :: Science/Research
Classifier: Natural Language :: English
Classifier: Natural Language :: Portuguese (Brazilian)
Classifier: Operating System :: OS Independent
Classifier: Programming Language :: Python :: 3
Classifier: License :: OSI Approved :: MIT License
Classifier: Topic :: Office/Business :: Financial
Classifier: Topic :: Scientific/Engineering :: Information Analysis
Classifier: Topic :: Utilities
Requires-Python: >=3.8
License-File: LICENSE.txt
Requires-Dist: numpy
Requires-Dist: pandas
Requires-Dist: mplfinance
Dynamic: license-file
